synophotos/__init__.py
synophotos/__main__.py
synophotos/cache.py
synophotos/cli.py
synophotos/error_codes.py
synophotos/exif.py
synophotos/fsio.py
synophotos/photos.py
synophotos/ui.py
synophotos/webapi.py
synophotos/webservice.py
synophotos/parameters/__init__.py
synophotos/parameters/photos.py
synophotos/parameters/webservice.py
synophotos-0.2.3.dist-info/entry_points.txt
synophotos-0.2.3.dist-info/LICENSE
synophotos-0.2.3.dist-info/WHEEL
synophotos-0.2.3.dist-info/METADATA
synophotos-0.2.3.dist-info/RECORD
