Metadata-Version: 2.1
Name: synophotos
Version: 0.2.3
Summary: Command Line Interface Client for Synology Photos
Keywords: synology,photos,terminal,cli,command line
Author-email: fortysix2ahead <fortysix2ahead@gmail.com>
Maintainer-email: fortysix2ahead <fortysix2ahead@gmail.com>
Requires-Python: >=3.9
Classifier: License :: OSI Approved :: MIT License
Classifier: Operating System :: OS Independent
Classifier: Programming Language :: Python
Classifier: Programming Language :: Python :: 3
Requires-Dist: attrs ~= 23.1.0
Requires-Dist: cattrs >= 23.1.2,< 23.3.0
Requires-Dist: click ~= 8.1.7
Requires-Dist: exif ~= 1.6.0
Requires-Dist: fs ~= 2.4.16
Requires-Dist: more-itertools ~= 10.1.0
Requires-Dist: platformdirs ~= 4.0.0
Requires-Dist: pyyaml ~= 6.0.1
Requires-Dist: requests ~= 2.31.0
Requires-Dist: rich >= 13.6,< 13.8
Requires-Dist: typing_extensions ~= 4.8.0
Requires-Dist: bumpver~=2023.1129 ; extra == "dev"
Requires-Dist: flit~=3.9.0 ; extra == "dev"
Requires-Dist: mkdocs~=1.5.3 ; extra == "dev"
Requires-Dist: mkdocs-click~=0.8.1 ; extra == "dev"
Requires-Dist: mkdocs-material~=9.4.7 ; extra == "dev"
Project-URL: Documentation, https://synophotos.readthedocs.io/
Project-URL: Homepage, https://github.com/fortysix2ahead/synophotos/
Project-URL: Issue Tracker, https://github.com/fortysix2ahead/synophotos/issues/
Project-URL: Source, https://github.com/fortysix2ahead/synophotos/
Project-URL: Source Code, https://github.com/fortysix2ahead/synophotos/
Provides-Extra: dev
